asaas/__init__.py
asaas/customers.py
asaas/exceptions.py
asaas/payments.py
asaas/pix.py
asaas/utils.py
asaas_sdk-3.3.1.dist-info/LICENSE
asaas_sdk-3.3.1.dist-info/METADATA
asaas_sdk-3.3.1.dist-info/WHEEL
asaas_sdk-3.3.1.dist-info/top_level.txt
asaas_sdk-3.3.1.dist-info/RECORD
