Metadata-Version: 2.1
Name: asaas-sdk
Version: 3.3.1
Summary: Biblioteca não oficial de comunicação com a API de pagamento do ASAAS
Author-email: Gabriel Niziolek <ganiziolek@gmail.com>
Project-URL: Homepage, https://github.com/GaNiziolek/asaas-sdk
Project-URL: Bug Tracker, https://github.com/GaNiziolek/asaas-sdk/issues
Keywords: asaas,sdk,payment
Classifier: Programming Language :: Python :: 3
Classifier: License :: OSI Approved :: MIT License
Classifier: Operating System :: OS Independent
Classifier: Development Status :: 4 - Beta
Requires-Python: >=3.10
License-File: LICENSE
Requires-Dist: requests>=2.28
Requires-Dist: jsonpickle>=3.0.0
Requires-Dist: python-dotenv>=0.21.0
